hatchbuck/__init__.py
hatchbuck/api.py
hatchbuck/objects.py
hatchbuck/primatives.py
pyhatchbuck-0.4.dist-info/LICENSE
pyhatchbuck-0.4.dist-info/WHEEL
pyhatchbuck-0.4.dist-info/METADATA
pyhatchbuck-0.4.dist-info/RECORD
