Metadata-Version: 2.1
Name: pyhatchbuck
Version: 0.4
Summary: Python library for Hatchbuck API
Home-page: https://github.com/jakesen/pyhatchbuck
License: MIT
Author: Jacob Senecal
Author-email: jacob.senecal@gmail.com
Requires-Python: >=2.7, !=3.0.*, !=3.1.*, !=3.2.*, !=3.3.*, !=3.4.*, !=3.5.*, !=3.6.*
Classifier: License :: OSI Approved :: MIT License
Classifier: Programming Language :: Python :: 2
Classifier: Programming Language :: Python :: 2.7
Classifier: Programming Language :: Python :: 3
Classifier: Programming Language :: Python :: 3.7
Requires-Dist: requests (>=2.22,<3.0)
Project-URL: Repository, https://github.com/jakesen/pyhatchbuck
